lexlib/__init__.py
lexlib/consonant_clusters.py
lexlib/io.py
lexlib/neighbors.py
lexlib/syllables.py
lexlib/utilities.py
lexlib-2.2.2.dist-info/METADATA
lexlib-2.2.2.dist-info/RECORD
lexlib-2.2.2.dist-info/WHEEL
lexlib-2.2.2.dist-info/top_level.txt
