Metadata-Version: 2.1
Name: lexlib
Version: 2.2.2
Summary: Utilities for research involving words.
Home-page: https://github.com/cranndarach/lexlib
Author: R. J. Steiner
Author-email: r.steiner@uconn.edu
License: MIT
Download-URL: https://github.com/cranndarach/lexlib/tarball/2.2.2
Project-URL: Documentation, https://lexlib.readthedocs.io
Keywords: psycholinguistics research words language linguistics                 psychology cognitive science cogsci
Platform: UNKNOWN
Classifier: Programming Language :: Python :: 3
Classifier: Development Status :: 4 - Beta
Classifier: Intended Audience :: Science/Research
Classifier: License :: OSI Approved :: MIT License
